LICENSE
MANIFEST.in
README.rst
setup.py
Hedwig.egg-info/PKG-INFO
Hedwig.egg-info/SOURCES.txt
Hedwig.egg-info/dependency_links.txt
Hedwig.egg-info/top_level.txt
hedwig/__init__.py
hedwig/message.py
hedwig/backends/__init__.py
hedwig/backends/base.py
hedwig/backends/console.py
hedwig/backends/smtp.py