Metadata-Version: 1.0
Name: Hedwig
Version: 0.1
Summary: django.core.mail without django.
Home-page: https://github.com/kimjayd/hedwig
Author: Hyunjun Kim
Author-email: kim@hyunjun.kr
License: MIT
Platform: any
